md2anki/__init__.py
md2anki/__main__.py
md2anki/anki_deck.py
md2anki/anki_model.py
md2anki/anki_note.py
md2anki/cli.py
md2anki/create_id.py
md2anki/entry_point.py
md2anki/evaluate_code.py
md2anki/html_util.py
md2anki/main.py
md2anki/md_parser.py
md2anki/md_to_pdf.py
md2anki/md_util.py
md2anki/note_models.py
md2anki/preprocessor.py
md2anki/subprocess.py
md2anki/svg_metadata.py
md2anki/info/__init__.py
md2anki/info/anki.py
md2anki/info/evaluate_code.py
md2anki/info/files.py
md2anki/info/general.py
md2anki/res/stylesheet.css
md2anki/res/stylesheet_type_answer.css
md2anki/res/stylesheet_type_cloze.css
md2anki-3.1.0.dist-info/licenses/LICENSE
md2anki-3.1.0.dist-info/METADATA
md2anki-3.1.0.dist-info/WHEEL
md2anki-3.1.0.dist-info/entry_points.txt
md2anki-3.1.0.dist-info/top_level.txt
md2anki-3.1.0.dist-info/RECORD
