Metadata-Version: 2.4
Name: md2anki
Version: 3.1.0
Summary: Convert Markdown formatted documents to anki decks
Home-page: https://github.com/AnonymerNiklasistanonym/Md2Anki
Author: AnonymerNiklasistanonym
License: MIT
Project-URL: Bug Tracker, https://github.com/AnonymerNiklasistanonym/Md2Anki/issues
Classifier: Programming Language :: Python :: 3
Classifier: License :: OSI Approved :: MIT License
Classifier: Operating System :: OS Independent
Requires-Python: >=3.9
License-File: LICENSE
Requires-Dist: beautifulsoup4>=4.12.2
Requires-Dist: genanki>=0.13.0
Requires-Dist: Markdown>=3.5
Requires-Dist: Pygments>=2.16.1
Dynamic: author
Dynamic: classifier
Dynamic: description
Dynamic: description-content-type
Dynamic: home-page
Dynamic: license
Dynamic: license-file
Dynamic: project-url
Dynamic: requires-dist
Dynamic: requires-python
Dynamic: summary
